__init__.py
watchdog.py
interpreters/get_input.py
interpreters/get_type.py
model_objects/base_model.py
model_objects/onnx_model.py
model_objects/tensorflow_keras_model.py
model_objects/tensorflow_savedmodel_model.py
model_objects/test.py
model_objects/tflite_model.py
watchdag-0.0.1a0.dist-info/LICENSE
watchdag-0.0.1a0.dist-info/METADATA
watchdag-0.0.1a0.dist-info/WHEEL
watchdag-0.0.1a0.dist-info/top_level.txt
watchdag-0.0.1a0.dist-info/RECORD
