Metadata-Version: 2.1
Name: watchdag
Version: 0.0.1a0
Summary: A simple watchdog class to store and manage configurations.
Author-email: Neosensory <zang@neosensory.com>
License: MIT License
Keywords: dictionary,config
Classifier: License :: OSI Approved :: MIT License
Classifier: Programming Language :: Python
Classifier: Programming Language :: Python :: 3
Requires-Python: >=3.9
License-File: LICENSE
